checkbox_parser/__init__.py
checkbox_parser-0.0.1.dist-info/LICENSE
checkbox_parser-0.0.1.dist-info/METADATA
checkbox_parser-0.0.1.dist-info/WHEEL
checkbox_parser-0.0.1.dist-info/top_level.txt
checkbox_parser-0.0.1.dist-info/RECORD
