Metadata-Version: 2.1
Name: checkbox-parser
Version: 0.0.1
Summary: this package can parse a list and give a html string
Home-page: https://github.com/richyxi/checkbox_parser
Author: ricardo cantu
Author-email: ricardocantum@gmail.com
License: UNKNOWN
Project-URL: Bug Tracker, https://github.com/richyxi/checkbox_parser/issues
Platform: UNKNOWN
Classifier: Programming Language :: Python :: 3
Classifier: License :: OSI Approved :: MIT License
Classifier: Operating System :: OS Independent
Requires-Python: >=3.6
License-File: LICENSE
